pedalboard_native.cpython-311-darwin.so
pedalboard/__init__.py
pedalboard/_pedalboard.py
pedalboard/midi_utils.py
pedalboard/py.typed
pedalboard/version.py
pedalboard/io/__init__.py
pedalboard_native/__init__.pyi
pedalboard_native/_internal/__init__.pyi
pedalboard_native/io/__init__.pyi
pedalboard_native/utils/__init__.pyi
pedalboard_benbenz-0.8.8.dist-info/LICENSE
pedalboard_benbenz-0.8.8.dist-info/METADATA
pedalboard_benbenz-0.8.8.dist-info/NOTICE
pedalboard_benbenz-0.8.8.dist-info/WHEEL
pedalboard_benbenz-0.8.8.dist-info/top_level.txt
pedalboard_benbenz-0.8.8.dist-info/RECORD
